reverse_pdb/__init__.py
reverse_pdb/reverse_pdb.py
reverse_pdb-0.0.1.dist-info/METADATA
reverse_pdb-0.0.1.dist-info/WHEEL
reverse_pdb-0.0.1.dist-info/top_level.txt
reverse_pdb-0.0.1.dist-info/RECORD
