Metadata-Version: 2.4
Name: reverse_pdb
Version: 0.0.1
Summary: Remote debugging with pdb using reverse and direct connections
Author-email: Ulises <ulises.odysseus22@gmail.com>
License: MIT
Project-URL: Homepage, https://github.com/ulisesojeda/py_remote_debugger
Requires-Python: >=3.6
